task2/counter.sv
module counter #(
    parameter WIDTH = 8
)(
    // interface signals
    input logic              clk,    // clock
    input logic              rst,   // reset
    input logic              en,    // counter enable
    output logic [WIDTH-1:0] count    // clock
);

always_ff @ (posedge clk)
    if (rst) count <= {WIDTH{1'b0}};
    else count <= count + {{WIDTH-1{1'b0}}, en};
        
endmodule

task3/ram2ports.sv
module ram2ports #(
    parameter ADDRESS_WIDTH = 8,
    parameter DATA_WIDTH = 8
)(
    input logic clk,
    input logic wr_en,
    input logic rd_en,
    input logic [ADDRESS_WIDTH-1:0] wr_addr,
    input logic [ADDRESS_WIDTH-1:0] rd_addr,
    input logic [DATA_WIDTH-1:0] din,
    output logic [DATA_WIDTH-1:0] dout
);

logic [DATA_WIDTH-1:0] ram_array [2**ADDRESS_WIDTH-1:0];

always_ff @(posedge clk) begin
    if (wr_en == 1'b1)
        ram_array[wr_addr] <= din;
    if (rd_en == 1'b1)
        // output is synchronous
        dout <= ram_array [rd_addr];
end
 endmodule

task3/sigdelay.sv
module sigdelay (
    input logic clk,
    input logic rst,
    input logic wr, // write enable for the RAM
    input logic rd, // read enable for the RAM
    input logic [8:0] offset, // Offset for reading from the RAM
    input logic [7:0] mic_signal, // Input signal from the microphone
    output logic [7:0] delayed_signal // Delayed output signal
);

    // The write address will be managed by a simple counter that wraps around.
    logic [8:0] wr_addr;
    logic [8:0] rd_addr; // Read address is the write address minus the offset
    logic [7:0] ram_dout; // Data output from the RAM

    // Instantiate the 2-port RAM
    ram2ports #(.ADDRESS_WIDTH(9), .DATA_WIDTH(8)) ram_inst (
        .clk(clk),
        .wr_en(wr),
        .rd_en(rd),
        .wr_addr(wr_addr),
        .rd_addr(rd_addr),
        .din(mic_signal),
        .dout(ram_dout)
    );

    // Instantiate the counter for the write address
    counter #(.WIDTH(9)) counter_inst (
        .clk(clk),
        .rst(rst),
        .en(wr), // Increment the counter on every write cycle
        .count(wr_addr)
    );

    // Calculate the read address based on the write address and the provided offset
    // always_comb begin
    //     rd_addr = (wr_addr >= offset) ? (wr_addr - offset) : (512 + wr_addr - offset);
    // end

    assign rd_addr = wr_addr - offset;

    // The output of the module is the data output from the RAM
    assign delayed_signal = ram_dout;

endmodule

task3/sigdelay.vcd
$version Generated by VerilatedVcd $end
$timescale 1ps $end

 $scope module TOP $end
  $var wire  1 # clk $end
  $var wire  8 ) delayed_signal [7:0] $end
  $var wire  8 ( mic_signal [7:0] $end
  $var wire  9 ' offset [8:0] $end
  $var wire  1 & rd $end
  $var wire  1 $ rst $end
  $var wire  1 % wr $end
  $scope module sigdelay $end
   $var wire  1 # clk $end
   $var wire  8 ) delayed_signal [7:0] $end
   $var wire  8 ( mic_signal [7:0] $end
   $var wire  9 ' offset [8:0] $end
   $var wire  8 , ram_dout [7:0] $end
   $var wire  1 & rd $end
   $var wire  9 + rd_addr [8:0] $end
   $var wire  1 $ rst $end
   $var wire  1 % wr $end
   $var wire  9 * wr_addr [8:0] $end
   $scope module counter_inst $end
    $var wire 32 - WIDTH [31:0] $end
    $var wire  1 # clk $end
    $var wire  9 * count [8:0] $end
    $var wire  1 % en $end
    $var wire  1 $ rst $end
   $upscope $end
   $scope module ram_inst $end
    $var wire 32 - ADDRESS_WIDTH [31:0] $end
    $var wire 32 . DATA_WIDTH [31:0] $end
    $var wire  1 # clk $end
    $var wire  8 ( din [7:0] $end
    $var wire  8 , dout [7:0] $end
    $var wire  9 + rd_addr [8:0] $end
    $var wire  1 & rd_en $end
    $var wire  9 * wr_addr [8:0] $end
    $var wire  1 % wr_en $end
   $upscope $end
  $upscope $end
 $upscope $end
$enddefinitions $end


#0
1#
0$
1%
1&
b001000000 '
b00000000 (
b00000000 )
b000000000 *
b111000000 +
b00000000 ,
b00000000000000000000000000001001 -
b00000000000000000000000000001000 .
#1
0#
#2
1#
b01100110 (
b000000001 *
b111000001 +
#3
0#
#4
1#
b01101101 (
b000000010 *
b111000010 +
#5
0#
#6
1#
b01101011 (
b000000011 *
b111000011 +
#7
0#
#8
1#
b01101001 (
b000000100 *
b111000100 +
#9
0#
#10
1#
b01101010 (
b000000101 *
b111000101 +
#11
0#
#12
1#
b01101000 (
b000000110 *
b111000110 +
#13
0#
#14
1#
b01101101 (
b000000111 *
b111000111 +
#15
0#
#16
1#
b01101010 (
b000001000 *
b111001000 +
#17
0#
#18
1#
b01101101 (
b000001001 *
b111001001 +
#19
0#
#20
1#
b000001010 *
b111001010 +
#21
0#
#22
1#
b01101001 (
b000001011 *
b111001011 +
#23
0#
#24
1#
b01100110 (
b000001100 *
b111001100 +
#25
0#
#26
1#
b01101001 (
b000001101 *
b111001101 +
#27
0#
#28
1#
b01101000 (
b000001110 *
b111001110 +
#29
0#
#30
1#
b01101011 (
b000001111 *
b111001111 +
#31
0#
#32
1#
b01100111 (
b000010000 *
b111010000 +
#33
0#
#34
1#
b01101101 (
b000010001 *
b111010001 +
#35
0#
#36
1#
b01101010 (
b000010010 *
b111010010 +
#37
0#
#38
1#
b01101001 (
b000010011 *
b111010011 +
#39
0#
#40
1#
b01101000 (
b000010100 *
b111010100 +
#41
0#
#42
1#
b01100110 (
b000010101 *
b111010101 +
#43
0#
#44
1#
b01101001 (
b000010110 *
b111010110 +
#45
0#
#46
1#
b01101011 (
b000010111 *
b111010111 +
#47
0#
#48
1#
b000011000 *
b111011000 +
#49
0#
#50
1#
b000011001 *
b111011001 +
#51
0#
#52
1#
b01101001 (
b000011010 *
b111011010 +
#53
0#
#54
1#
b01101100 (
b000011011 *
b111011011 +
#55
0#
#56
1#
b01101001 (
b000011100 *
b111011100 +
#57
0#
#58
1#
b01101011 (
b000011101 *
b111011101 +
#59
0#
#60
1#
b01101100 (
b000011110 *
b111011110 +
#61
0#
#62
1#
b01101010 (
b000011111 *
b111011111 +
#63
0#
#64
1#
b01101001 (
b000100000 *
b111100000 +
#65
0#
#66
1#
b01101110 (
b000100001 *
b111100001 +
#67
0#
#68
1#
b01101100 (
b000100010 *
b111100010 +
#69
0#
#70
1#
b01101010 (
b000100011 *
b111100011 +
#71
0#
#72
1#
b01101000 (
b000100100 *
b111100100 +
#73
0#
#74
1#
b000100101 *
b111100101 +
#75
0#
#76
1#
b01101011 (
b000100110 *
b111100110 +
#77
0#
#78
1#
b01101100 (
b000100111 *
b111100111 +
#79
0#
#80
1#
b01101110 (
b000101000 *
b111101000 +
#81
0#
#82
1#
b01101001 (
b000101001 *
b111101001 +
#83
0#
#84
1#
b01101011 (
b000101010 *
b111101010 +
#85
0#
#86
1#
b01101100 (
b000101011 *
b111101011 +
#87
0#
#88
1#
b000101100 *
b111101100 +
#89
0#
#90
1#
b01101101 (
b000101101 *
b111101101 +
#91
0#
#92
1#
b000101110 *
b111101110 +
#93
0#
#94
1#
b01101000 (
b000101111 *
b111101111 +
#95
0#
#96
1#
b01101100 (
b000110000 *
b111110000 +
#97
0#
#98
1#
b01101001 (
b000110001 *
b111110001 +
#99
0#
#100
1#
b01101011 (
b000110010 *
b111110010 +
#101
0#
#102
1#
b01101100 (
b000110011 *
b111110011 +
#103
0#
#104
1#
b01100101 (
b000110100 *
b111110100 +
#105
0#
#106
1#
b01101010 (
b000110101 *
b111110101 +
#107
0#
#108
1#
b000110110 *
b111110110 +
#109
0#
#110
1#
b01101100 (
b000110111 *
b111110111 +
#111
0#
#112
1#
b01101001 (
b000111000 *
b111111000 +
#113
0#
#114
1#
b01100111 (
b000111001 *
b111111001 +
#115
0#
#116
1#
b01101000 (
b000111010 *
b111111010 +
#117
0#
#118
1#
b01101010 (
b000111011 *
b111111011 +
#119
0#
#120
1#
b01101001 (
b000111100 *
b111111100 +
#121
0#
#122
1#
b01110000 (
b000111101 *
b111111101 +
#123
0#
#124
1#
b01101001 (
b000111110 *
b111111110 +
#125
0#
#126
1#
b000111111 *
b111111111 +
#127
0#
#128
1#
b001000000 *
b000000000 +
#129
0#
#130
1#
b01101111 (
b001000001 *
b000000001 +
#131
0#
#132
1#
b01101010 (
b01100110 )
b001000010 *
b000000010 +
b01100110 ,
#133
0#
#134
1#
b01101000 (
b01101101 )
b001000011 *
b000000011 +
b01101101 ,
#135
0#
#136
1#
b01101010 (
b01101011 )
b001000100 *
b000000100 +
b01101011 ,
#137
0#
#138
1#
b01101100 (
b01101001 )
b001000101 *
b000000101 +
b01101001 ,
#139
0#
#140
1#
b01101011 (
b01101010 )
b001000110 *
b000000110 +
b01101010 ,
#141
0#
#142
1#
b01101100 (
b01101000 )
b001000111 *
b000000111 +
b01101000 ,
#143
0#
#144
1#
b01101101 )
b001001000 *
b000001000 +
b01101101 ,
#145
0#
#146
1#
b01101010 )
b001001001 *
b000001001 +
b01101010 ,
#147
0#
#148
1#
b01101010 (
b01101101 )
b001001010 *
b000001010 +
b01101101 ,
#149
0#
#150
1#
b01101110 (
b001001011 *
b000001011 +
#151
0#
#152
1#
b01110010 (
b01101001 )
b001001100 *
b000001100 +
b01101001 ,
#153
0#
#154
1#
b01110000 (
b01100110 )
b001001101 *
b000001101 +
b01100110 ,
#155
0#
#156
1#
b01101010 (
b01101001 )
b001001110 *
b000001110 +
b01101001 ,
#157
0#
#158
1#
b01101100 (
b01101000 )
b001001111 *
b000001111 +
b01101000 ,
#159
0#
#160
1#
b01101011 )
b001010000 *
b000010000 +
b01101011 ,
#161
0#
#162
1#
b01101000 (
b01100111 )
b001010001 *
b000010001 +
b01100111 ,
#163
0#
#164
1#
b01101010 (
b01101101 )
b001010010 *
b000010010 +
b01101101 ,
#165
0#
#166
1#
b01101001 (
b01101010 )
b001010011 *
b000010011 +
b01101010 ,
#167
0#
#168
1#
b01101000 (
b01101001 )
b001010100 *
b000010100 +
b01101001 ,
#169
0#
#170
1#
b01101000 )
b001010101 *
b000010101 +
b01101000 ,
#171
0#
#172
1#
b01101011 (
b01100110 )
b001010110 *
b000010110 +
b01100110 ,
#173
0#
#174
1#
b01101010 (
b01101001 )
b001010111 *
b000010111 +
b01101001 ,
#175
0#
#176
1#
b01101011 (
b01101011 )
b001011000 *
b000011000 +
b01101011 ,
#177
0#
#178
1#
b01101100 (
b001011001 *
b000011001 +
#179
0#
#180
1#
b01101010 (
b001011010 *
b000011010 +
#181
0#
#182
1#
b01101011 (
b01101001 )
b001011011 *
b000011011 +
b01101001 ,
#183
0#
#184
1#
b01101001 (
b01101100 )
b001011100 *
b000011100 +
b01101100 ,
#185
0#
#186
1#
b01101101 (
b01101001 )
b001011101 *
b000011101 +
b01101001 ,
#187
0#
#188
1#
b01101000 (
b01101011 )
b001011110 *
b000011110 +
b01101011 ,
#189
0#
#190
1#
b01110001 (
b01101100 )
b001011111 *
b000011111 +
b01101100 ,
#191
0#
#192
1#
b01101101 (
b01101010 )
b001100000 *
b000100000 +
b01101010 ,
#193
0#
#194
1#
b01101010 (
b01101001 )
b001100001 *
b000100001 +
b01101001 ,
#195
0#
#196
1#
b01101110 )
b001100010 *
b000100010 +
b01101110 ,
#197
0#
#198
1#
b01101100 (
b01101100 )
b001100011 *
b000100011 +
b01101100 ,
#199
0#
#200
1#
b01101010 (
b01101010 )
b001100100 *
b000100100 +
b01101010 ,
#201
0#
#202
1#
b01101000 (
b01101000 )
b001100101 *
b000100101 +
b01101000 ,
#203
0#
#204
1#
b001100110 *
b000100110 +
#205
0#
#206
1#
b01101101 (
b01101011 )
b001100111 *
b000100111 +
b01101011 ,
#207
0#
#208
1#
b01101100 )
b001101000 *
b000101000 +
b01101100 ,
#209
0#
#210
1#
b01101110 (
b01101110 )
b001101001 *
b000101001 +
b01101110 ,
#211
0#
#212
1#
b01101100 (
b01101001 )
b001101010 *
b000101010 +
b01101001 ,
#213
0#
#214
1#
b01101010 (
b01101011 )
b001101011 *
b000101011 +
b01101011 ,
#215
0#
#216
1#
b01101100 (
b01101100 )
b001101100 *
b000101100 +
b01101100 ,
#217
0#
#218
1#
b01101011 (
b001101101 *
b000101101 +
#219
0#
#220
1#
b01101101 )
b001101110 *
b000101110 +
b01101101 ,
#221
0#
#222
1#
b01101100 (
b001101111 *
b000101111 +
#223
0#
#224
1#
b01101001 (
b01101000 )
b001110000 *
b000110000 +
b01101000 ,
#225
0#
#226
1#
b01101010 (
b01101100 )
b001110001 *
b000110001 +
b01101100 ,
#227
0#
#228
1#
b01101001 )
b001110010 *
b000110010 +
b01101001 ,
#229
0#
#230
1#
b01101011 (
b01101011 )
b001110011 *
b000110011 +
b01101011 ,
#231
0#
#232
1#
b01101001 (
b01101100 )
b001110100 *
b000110100 +
b01101100 ,
#233
0#
#234
1#
b01101100 (
b01100101 )
b001110101 *
b000110101 +
b01100101 ,
#235
0#
#236
1#
b01101110 (
b01101010 )
b001110110 *
b000110110 +
b01101010 ,
#237
0#
#238
1#
b01110000 (
b001110111 *
b000110111 +
#239
0#
#240
1#
b01101101 (
b01101100 )
b001111000 *
b000111000 +
b01101100 ,
#241
0#
#242
1#
b01101110 (
b01101001 )
b001111001 *
b000111001 +
b01101001 ,
#243
0#
#244
1#
b01101100 (
b01100111 )
b001111010 *
b000111010 +
b01100111 ,
#245
0#
#246
1#
b01101110 (
b01101000 )
b001111011 *
b000111011 +
b01101000 ,
#247
0#
#248
1#
b01101100 (
b01101010 )
b001111100 *
b000111100 +
b01101010 ,
#249
0#
#250
1#
b01101001 )
b001111101 *
b000111101 +
b01101001 ,
#251
0#
#252
1#
b01101011 (
b01110000 )
b001111110 *
b000111110 +
b01110000 ,
#253
0#
#254
1#
b01101101 (
b01101001 )
b001111111 *
b000111111 +
b01101001 ,
#255
0#
#256
1#
b01101010 (
b010000000 *
b001000000 +
#257
0#
#258
1#
b01101000 (
b010000001 *
b001000001 +
#259
0#
#260
1#
b01101100 (
b01101111 )
b010000010 *
b001000010 +
b01101111 ,
#261
0#
#262
1#
b01101001 (
b01101010 )
b010000011 *
b001000011 +
b01101010 ,
#263
0#
#264
1#
b01101111 (
b01101000 )
b010000100 *
b001000100 +
b01101000 ,
#265
0#
#266
1#
b01101001 (
b01101010 )
b010000101 *
b001000101 +
b01101010 ,
#267
0#
#268
1#
b01101101 (
b01101100 )
b010000110 *
b001000110 +
b01101100 ,
#269
0#
#270
1#
b01100111 (
b01101011 )
b010000111 *
b001000111 +
b01101011 ,
#271
0#
#272
1#
b01101000 (
b01101100 )
b010001000 *
b001001000 +
b01101100 ,
#273
0#
#274
1#
b01101001 (
b010001001 *
b001001001 +
#275
0#
#276
1#
b01100110 (
b010001010 *
b001001010 +
#277
0#
#278
1#
b01101011 (
b01101010 )
b010001011 *
b001001011 +
b01101010 ,
#279
0#
#280
1#
b01101101 (
b01101110 )
b010001100 *
b001001100 +
b01101110 ,
#281
0#
#282
1#
b01101100 (
b01110010 )
b010001101 *
b001001101 +
b01110010 ,
#283
0#
#284
1#
b01101001 (
b01110000 )
b010001110 *
b001001110 +
b01110000 ,
#285
0#
#286
1#
b01101011 (
b01101010 )
b010001111 *
b001001111 +
b01101010 ,
#287
0#
#288
1#
b01101010 (
b01101100 )
b010010000 *
b001010000 +
b01101100 ,
#289
0#
#290
1#
b01100101 (
b010010001 *
b001010001 +
#291
0#
#292
1#
b01100110 (
b01101000 )
b010010010 *
b001010010 +
b01101000 ,
#293
0#
#294
1#
b01101010 )
b010010011 *
b001010011 +
b01101010 ,
#295
0#
#296
1#
b01101001 (
b01101001 )
b010010100 *
b001010100 +
b01101001 ,
#297
0#
#298
1#
b01101110 (
b01101000 )
b010010101 *
b001010101 +
b01101000 ,
#299
0#
#300
1#
b01101011 (
b010010110 *
b001010110 +
#301
0#
#302
1#
b01101001 (
b01101011 )
b010010111 *
b001010111 +
b01101011 ,
#303
0#
#304
1#
b01101010 (
b01101010 )
b010011000 *
b001011000 +
b01101010 ,
#305
0#
#306
1#
b01100111 (
b01101011 )
b010011001 *
b001011001 +
b01101011 ,
#307
0#
#308
1#
b01101001 (
b01101100 )
b010011010 *
b001011010 +
b01101100 ,
#309
0#
#310
1#
b01101010 )
b010011011 *
b001011011 +
b01101010 ,
#311
0#
#312
1#
b01101111 (
b01101011 )
b010011100 *
b001011100 +
b01101011 ,
#313
0#
#314
1#
b01101100 (
b01101001 )
b010011101 *
b001011101 +
b01101001 ,
#315
0#
#316
1#
b01101010 (
b01101101 )
b010011110 *
b001011110 +
b01101101 ,
#317
0#
#318
1#
b01101001 (
b01101000 )
b010011111 *
b001011111 +
b01101000 ,
#319
0#
#320
1#
b01110001 )
b010100000 *
b001100000 +
b01110001 ,
#321
0#
#322
1#
b01101011 (
b01101101 )
b010100001 *
b001100001 +
b01101101 ,
#323
0#
#324
1#
b01101100 (
b01101010 )
b010100010 *
b001100010 +
b01101010 ,
#325
0#
#326
1#
b01101011 (
b010100011 *
b001100011 +
#327
0#
#328
1#
b01101100 )
b010100100 *
b001100100 +
b01101100 ,
#329
0#
#330
1#
b01101001 (
b01101010 )
b010100101 *
b001100101 +
b01101010 ,
#331
0#
#332
1#
b01101011 (
b01101000 )
b010100110 *
b001100110 +
b01101000 ,
#333
0#
#334
1#
b01101100 (
b010100111 *
b001100111 +
#335
0#
#336
1#
b01101011 (
b01101101 )
b010101000 *
b001101000 +
b01101101 ,
#337
0#
#338
1#
b01101001 (
b010101001 *
b001101001 +
#339
0#
#340
1#
b01110000 (
b01101110 )
b010101010 *
b001101010 +
b01101110 ,
#341
0#
#342
1#
b01101001 (
b01101100 )
b010101011 *
b001101011 +
b01101100 ,
#343
0#
#344
1#
b01101110 (
b01101010 )
b010101100 *
b001101100 +
b01101010 ,
#345
0#
#346
1#
b01101010 (
b01101100 )
b010101101 *
b001101101 +
b01101100 ,
#347
0#
#348
1#
b01101100 (
b01101011 )
b010101110 *
b001101110 +
b01101011 ,
#349
0#
#350
1#
b01101011 (
b010101111 *
b001101111 +
#351
0#
#352
1#
b01101100 (
b01101100 )
b010110000 *
b001110000 +
b01101100 ,
#353
0#
#354
1#
b01101101 (
b01101001 )
b010110001 *
b001110001 +
b01101001 ,
#355
0#
#356
1#
b01101001 (
b01101010 )
b010110010 *
b001110010 +
b01101010 ,
#357
0#
#358
1#
b01101010 (
b010110011 *
b001110011 +
#359
0#
#360
1#
b01101100 (
b01101011 )
b010110100 *
b001110100 +
b01101011 ,
#361
0#
#362
1#
b01101110 (
b01101001 )
b010110101 *
b001110101 +
b01101001 ,
#363
0#
#364
1#
b01101111 (
b01101100 )
b010110110 *
b001110110 +
b01101100 ,
#365
0#
#366
1#
b01101000 (
b01101110 )
b010110111 *
b001110111 +
b01101110 ,
#367
0#
#368
1#
b01101110 (
b01110000 )
b010111000 *
b001111000 +
b01110000 ,
#369
0#
#370
1#
b01101010 (
b01101101 )
b010111001 *
b001111001 +
b01101101 ,
#371
0#
#372
1#
b01100111 (
b01101110 )
b010111010 *
b001111010 +
b01101110 ,
#373
0#
#374
1#
b01101001 (
b01101100 )
b010111011 *
b001111011 +
b01101100 ,
#375
0#
#376
1#
b01101101 (
b01101110 )
b010111100 *
b001111100 +
b01101110 ,
#377
0#
#378
1#
b01101011 (
b01101100 )
b010111101 *
b001111101 +
b01101100 ,
#379
0#
#380
1#
b01100110 (
b010111110 *
b001111110 +
#381
0#
#382
1#
b01101000 (
b01101011 )
b010111111 *
b001111111 +
b01101011 ,
#383
0#
#384
1#
b01101101 )
b011000000 *
b010000000 +
b01101101 ,
#385
0#
#386
1#
b01101001 (
b01101010 )
b011000001 *
b010000001 +
b01101010 ,
#387
0#
#388
1#
b01101011 (
b01101000 )
b011000010 *
b010000010 +
b01101000 ,
#389
0#
#390
1#
b01101101 (
b01101100 )
b011000011 *
b010000011 +
b01101100 ,
#391
0#
#392
1#
b01101010 (
b01101001 )
b011000100 *
b010000100 +
b01101001 ,
#393
0#
#394
1#
b01101111 )
b011000101 *
b010000101 +
b01101111 ,
#395
0#
#396
1#
b01101000 (
b01101001 )
b011000110 *
b010000110 +
b01101001 ,
#397
0#
#398
1#
b01101011 (
b01101101 )
b011000111 *
b010000111 +
b01101101 ,
#399
0#
#400
1#
b01101110 (
b01100111 )
b011001000 *
b010001000 +
b01100111 ,
#401
0#
#402
1#
b01101000 )
b011001001 *
b010001001 +
b01101000 ,
#403
0#
#404
1#
b01110000 (
b01101001 )
b011001010 *
b010001010 +
b01101001 ,
#405
0#
#406
1#
b01101010 (
b01100110 )
b011001011 *
b010001011 +
b01100110 ,
#407
0#
#408
1#
b01100111 (
b01101011 )
b011001100 *
b010001100 +
b01101011 ,
#409
0#
#410
1#
b01101110 (
b01101101 )
b011001101 *
b010001101 +
b01101101 ,
#411
0#
#412
1#
b01101000 (
b01101100 )
b011001110 *
b010001110 +
b01101100 ,
#413
0#
#414
1#
b01101101 (
b01101001 )
b011001111 *
b010001111 +
b01101001 ,
#415
0#
#416
1#
b01101001 (
b01101011 )
b011010000 *
b010010000 +
b01101011 ,
#417
0#
#418
1#
b01101011 (
b01101010 )
b011010001 *
b010010001 +
b01101010 ,
#419
0#
#420
1#
b01101001 (
b01100101 )
b011010010 *
b010010010 +
b01100101 ,
#421
0#
#422
1#
b01101111 (
b01100110 )
b011010011 *
b010010011 +
b01100110 ,
#423
0#
#424
1#
b01101110 (
b011010100 *
b010010100 +
#425
0#
#426
1#
b01101001 (
b01101001 )
b011010101 *
b010010101 +
b01101001 ,
#427
0#
#428
1#
b01101010 (
b01101110 )
b011010110 *
b010010110 +
b01101110 ,
#429
0#
#430
1#
b01101001 (
b01101011 )
b011010111 *
b010010111 +
b01101011 ,
#431
0#
#432
1#
b01101101 (
b01101001 )
b011011000 *
b010011000 +
b01101001 ,
#433
0#
#434
1#
b01101010 )
b011011001 *
b010011001 +
b01101010 ,
#435
0#
#436
1#
b01100111 )
b011011010 *
b010011010 +
b01100111 ,
#437
0#
#438
1#
b01101010 (
b01101001 )
b011011011 *
b010011011 +
b01101001 ,
#439
0#
#440
1#
b01101001 (
b011011100 *
b010011100 +
#441
0#
#442
1#
b01101100 (
b01101111 )
b011011101 *
b010011101 +
b01101111 ,
#443
0#
#444
1#
b01101100 )
b011011110 *
b010011110 +
b01101100 ,
#445
0#
#446
1#
b01101101 (
b01101010 )
b011011111 *
b010011111 +
b01101010 ,
#447
0#
#448
1#
b01101011 (
b01101001 )
b011100000 *
b010100000 +
b01101001 ,
#449
0#
#450
1#
b01101100 (
b011100001 *
b010100001 +
#451
0#
#452
1#
b01101110 (
b01101011 )
b011100010 *
b010100010 +
b01101011 ,
#453
0#
#454
1#
b01101101 (
b01101100 )
b011100011 *
b010100011 +
b01101100 ,
#455
0#
#456
1#
b01101010 (
b01101011 )
b011100100 *
b010100100 +
b01101011 ,
#457
0#
#458
1#
b011100101 *
b010100101 +
#459
0#
#460
1#
b01101101 (
b01101001 )
b011100110 *
b010100110 +
b01101001 ,
#461
0#
#462
1#
b01101011 (
b01101011 )
b011100111 *
b010100111 +
b01101011 ,
#463
0#
#464
1#
b01101000 (
b01101100 )
b011101000 *
b010101000 +
b01101100 ,
#465
0#
#466
1#
b01101001 (
b01101011 )
b011101001 *
b010101001 +
b01101011 ,
#467
0#
#468
1#
b01100111 (
b01101001 )
b011101010 *
b010101010 +
b01101001 ,
#469
0#
#470
1#
b01101010 (
b01110000 )
b011101011 *
b010101011 +
b01110000 ,
#471
0#
#472
1#
b01101000 (
b01101001 )
b011101100 *
b010101100 +
b01101001 ,
#473
0#
#474
1#
b01101110 )
b011101101 *
b010101101 +
b01101110 ,
#475
0#
#476
1#
b01101101 (
b01101010 )
b011101110 *
b010101110 +
b01101010 ,
#477
0#
#478
1#
b01101011 (
b01101100 )
b011101111 *
b010101111 +
b01101100 ,
#479
0#
#480
1#
b01101010 (
b01101011 )
b011110000 *
b010110000 +
b01101011 ,
#481
0#
#482
1#
b01101100 )
b011110001 *
b010110001 +
b01101100 ,
#483
0#
#484
1#
b01101100 (
b01101101 )
b011110010 *
b010110010 +
b01101101 ,
#485
0#
#486
1#
b01101010 (
b01101001 )
b011110011 *
b010110011 +
b01101001 ,
#487
0#
#488
1#
b01101100 (
b01101010 )
b011110100 *
b010110100 +
b01101010 ,
#489
0#
#490
1#
b01101101 (
b01101100 )
b011110101 *
b010110101 +
b01101100 ,
#491
0#
#492
1#
b01101000 (
b01101110 )
b011110110 *
b010110110 +
b01101110 ,
#493
0#
#494
1#
b01101100 (
b01101111 )
b011110111 *
b010110111 +
b01101111 ,
#495
0#
#496
1#
b01101011 (
b01101000 )
b011111000 *
b010111000 +
b01101000 ,
#497
0#
#498
1#
b01101001 (
b01101110 )
b011111001 *
b010111001 +
b01101110 ,
#499
0#
#500
1#
b01101010 )
b011111010 *
b010111010 +
b01101010 ,
#501
0#
#502
1#
b01101000 (
b01100111 )
b011111011 *
b010111011 +
b01100111 ,
#503
0#
#504
1#
b01101100 (
b01101001 )
b011111100 *
b010111100 +
b01101001 ,
#505
0#
#506
1#
b01101101 )
b011111101 *
b010111101 +
b01101101 ,
#507
0#
#508
1#
b01101111 (
b01101011 )
b011111110 *
b010111110 +
b01101011 ,
#509
0#
#510
1#
b01101001 (
b01100110 )
b011111111 *
b010111111 +
b01100110 ,
#511
0#
#512
1#
b01110000 (
b01101000 )
b100000000 *
b011000000 +
b01101000 ,
#513
0#
#514
1#
b01101000 (
b100000001 *
b011000001 +
#515
0#
#516
1#
b01101001 (
b01101001 )
b100000010 *
b011000010 +
b01101001 ,
#517
0#
#518
1#
b01101010 (
b01101011 )
b100000011 *
b011000011 +
b01101011 ,
#519
0#
#520
1#
b01110000 (
b01101101 )
b100000100 *
b011000100 +
b01101101 ,
#521
0#
#522
1#
b01101011 (
b01101010 )
b100000101 *
b011000101 +
b01101010 ,
#523
0#
#524
1#
b01101001 (
b100000110 *
b011000110 +
#525
0#
#526
1#
b01101010 (
b01101000 )
b100000111 *
b011000111 +
b01101000 ,
#527
0#
#528
1#
b01101110 (
b01101011 )
b100001000 *
b011001000 +
b01101011 ,
#529
0#
#530
1#
b01101101 (
b01101110 )
b100001001 *
b011001001 +
b01101110 ,
#531
0#
#532
1#
b01101010 (
b100001010 *
b011001010 +
#533
0#
#534
1#
b01101011 (
b01110000 )
b100001011 *
b011001011 +
b01110000 ,
#535
0#
#536
1#
b01101010 (
b01101010 )
b100001100 *
b011001100 +
b01101010 ,
#537
0#
#538
1#
b01101011 (
b01100111 )
b100001101 *
b011001101 +
b01100111 ,
#539
0#
#540
1#
b01101110 (
b01101110 )
b100001110 *
b011001110 +
b01101110 ,
#541
0#
#542
1#
b01101001 (
b01101000 )
b100001111 *
b011001111 +
b01101000 ,
#543
0#
#544
1#
b01100111 (
b01101101 )
b100010000 *
b011010000 +
b01101101 ,
#545
0#
#546
1#
b01101000 (
b01101001 )
b100010001 *
b011010001 +
b01101001 ,
#547
0#
#548
1#
b01101110 (
b01101011 )
b100010010 *
b011010010 +
b01101011 ,
#549
0#
#550
1#
b01101100 (
b01101001 )
b100010011 *
b011010011 +
b01101001 ,
#551
0#
#552
1#
b01101011 (
b01101111 )
b100010100 *
b011010100 +
b01101111 ,
#553
0#
#554
1#
b01101111 (
b01101110 )
b100010101 *
b011010101 +
b01101110 ,
#555
0#
#556
1#
b01101001 (
b01101001 )
b100010110 *
b011010110 +
b01101001 ,
#557
0#
#558
1#
b01101011 (
b01101010 )
b100010111 *
b011010111 +
b01101010 ,
#559
0#
#560
1#
b01101001 )
b100011000 *
b011011000 +
b01101001 ,
#561
0#
#562
1#
b01101001 (
b01101101 )
b100011001 *
b011011001 +
b01101101 ,
#563
0#
#564
1#
b01101000 (
b100011010 *
b011011010 +
#565
0#
#566
1#
b100011011 *
b011011011 +
#567
0#
#568
1#
b01101011 (
b01101010 )
b100011100 *
b011011100 +
b01101010 ,
#569
0#
#570
1#
b01101001 (
b01101001 )
b100011101 *
b011011101 +
b01101001 ,
#571
0#
#572
1#
b01101011 (
b01101100 )
b100011110 *
b011011110 +
b01101100 ,
#573
0#
#574
1#
b100011111 *
b011011111 +
#575
0#
#576
1#
b01101100 (
b01101101 )
b100100000 *
b011100000 +
b01101101 ,
#577
0#
#578
1#
b01101101 (
b01101011 )
b100100001 *
b011100001 +
b01101011 ,
#579
0#
#580
1#
b01101011 (
b01101100 )
b100100010 *
b011100010 +
b01101100 ,
#581
0#
#582
1#
b01101001 (
b01101110 )
b100100011 *
b011100011 +
b01101110 ,
#583
0#
#584
1#
b01101011 (
b01101101 )
b100100100 *
b011100100 +
b01101101 ,
#585
0#
#586
1#
b01101101 (
b01101010 )
b100100101 *
b011100101 +
b01101010 ,
#587
0#
#588
1#
b01101000 (
b100100110 *
b011100110 +
#589
0#
#590
1#
b01101010 (
b01101101 )
b100100111 *
b011100111 +
b01101101 ,
#591
0#
#592
1#
b01101011 )
b100101000 *
b011101000 +
b01101011 ,
#593
0#
#594
1#
b01101001 (
b01101000 )
b100101001 *
b011101001 +
b01101000 ,
#595
0#
#596
1#
b01101010 (
b01101001 )
b100101010 *
b011101010 +
b01101001 ,
#597
0#
#598
1#
b01101100 (
b01100111 )
b100101011 *
b011101011 +
b01100111 ,
#599
0#
#600
1#
b01101010 (
b01101010 )
b100101100 *
b011101100 +
b01101010 ,
#601
0#
#602
1#
b01101011 (
b01101000 )
b100101101 *
b011101101 +
b01101000 ,
#603
0#
#604
1#
b01101010 (
b100101110 *
b011101110 +
#605
0#
#606
1#
b01101011 (
b01101101 )
b100101111 *
b011101111 +
b01101101 ,
#607
0#
#608
1#
b01101101 (
b01101011 )
b100110000 *
b011110000 +
b01101011 ,
#609
0#
#610
1#
b01100110 (
b01101010 )
b100110001 *
b011110001 +
b01101010 ,
#611
0#
#612
1#
b01101010 (
b100110010 *
b011110010 +
#613
0#
#614
1#
b01101100 )
b100110011 *
b011110011 +
b01101100 ,
#615
0#
#616
1#
b01100111 (
b01101010 )
b100110100 *
b011110100 +
b01101010 ,
#617
0#
